LICENSE.txt
setup.py
abdalmjeedalhobany.egg-info/PKG-INFO
abdalmjeedalhobany.egg-info/SOURCES.txt
abdalmjeedalhobany.egg-info/dependency_links.txt
abdalmjeedalhobany.egg-info/top_level.txt
code/__init__.py
code/setup.py