Metadata-Version: 2.1
Name: abdalmjeedalhobany
Version: 0.0.1
Summary: simpel library in python
Author: abdalmjeedalhobany
Author-email: 
Classifier: Programming Language :: Python :: 3
Classifier: License :: OSI Approved :: MIT License
Classifier: Operating System :: OS Independent
License-File: LICENSE.txt
